test/__init__.py
test/test_experimentlogger.py
test/test_numpyseabornimageplotlogger.py
test/test_pytorchexperiment.py
test/test_pytorchexperimentlogger.py
test/test_pytorchtensorboardxlogger.py
test/test_pytorchvisdomlogger.py
trixi/__init__.py
trixi/browser.py
trixi/experiment/__init__.py
trixi/experiment/experiment.py
trixi/experiment/pytorchexperiment.py
trixi/experiment_browser/__init__.py
trixi/experiment_browser/browser.py
trixi/experiment_browser/dataprocessing.py
trixi/experiment_browser/experimentreader.py
trixi/experiment_browser/__pycache__/__init__.cpython-36.pyc
trixi/experiment_browser/__pycache__/__init__.cpython-37.pyc
trixi/experiment_browser/__pycache__/browser.cpython-36.pyc
trixi/experiment_browser/__pycache__/browser.cpython-37.pyc
trixi/experiment_browser/__pycache__/dataprocessing.cpython-36.pyc
trixi/experiment_browser/__pycache__/dataprocessing.cpython-37.pyc
trixi/experiment_browser/__pycache__/experimentreader.cpython-36.pyc
trixi/experiment_browser/__pycache__/experimentreader.cpython-37.pyc
trixi/experiment_browser/static/assets/trixi-icon.png
trixi/experiment_browser/static/assets/trixi-small.png
trixi/experiment_browser/static/css/custom.css
trixi/experiment_browser/static/js/scripts.js
trixi/experiment_browser/templates/experiment.html
trixi/experiment_browser/templates/overview.html
trixi/logger/__init__.py
trixi/logger/abstractlogger.py
trixi/logger/combinedlogger.py
trixi/logger/experiment/__init__.py
trixi/logger/experiment/experimentlogger.py
trixi/logger/experiment/pytorchexperimentlogger.py
trixi/logger/file/__init__.py
trixi/logger/file/numpyplotfilelogger.py
trixi/logger/file/pytorchplotfilelogger.py
trixi/logger/file/textfilelogger.py
trixi/logger/message/__init__.py
trixi/logger/message/slackmessagelogger.py
trixi/logger/message/telegrammessagelogger.py
trixi/logger/plt/__init__.py
trixi/logger/plt/numpyseabornimageplotlogger.py
trixi/logger/plt/numpyseabornplotlogger.py
trixi_slim-0.1.2.2.dist-info/METADATA
trixi_slim-0.1.2.2.dist-info/RECORD
trixi_slim-0.1.2.2.dist-info/WHEEL
trixi_slim-0.1.2.2.dist-info/entry_points.txt
trixi_slim-0.1.2.2.dist-info/top_level.txt
trixi_slim-0.1.2.2.dist-info/zip-safe
